sol1_monitoring_plugins_lib/__init__.py
sol1_monitoring_plugins_lib/logging.py
sol1_monitoring_plugins_lib/monitoring_plugins.py
sol1_monitoring_plugins_lib/requests.py
sol1_monitoring_plugins_lib-1.1.1.dist-info/LICENCE
sol1_monitoring_plugins_lib-1.1.1.dist-info/METADATA
sol1_monitoring_plugins_lib-1.1.1.dist-info/WHEEL
sol1_monitoring_plugins_lib-1.1.1.dist-info/top_level.txt
sol1_monitoring_plugins_lib-1.1.1.dist-info/RECORD
