Metadata-Version: 2.1
Name: sol1-monitoring-plugins-lib
Version: 1.1.1
Summary: Simple Library to manage the output for Nagios and Icinga Monitoring Plugins
Home-page: https://github.com/sol1/sol1-monitoring-plugins-lib
Author: Matthew Smith
Author-email: matthew.smith@sol1.com.au
Project-URL: Bug Tracker, https://github.com/sol1/sol1-monitoring-plugins-lib/issues
Classifier: Programming Language :: Python :: 3
Classifier: License :: OSI Approved :: MIT License
Classifier: Operating System :: OS Independent
Requires-Python: >=3.7
License-File: LICENCE
Requires-Dist: loguru
